[
    {
        "id": "_0m4gbtr5m",
        "number": 0,
        "title": "продам AUDI A6",
        "price": "133,200 грн",
        "year": "1997",
        "condition": "Хорошее",
        "engine": "2.8",
        "transmissionType": "Автомат",
        "location": "Харьков",
        "description": "Продам свою AUDI A6. Автомобиль в редком состоянии для этого года. Установлено новое дорогое ГБО. КПП автомат. Подогревы",
        "mileage": " 280000 - пробег",
        "updateDate": "17:57",
        "link": "http://rst.ua/oldcars/audi/a6/audi_a6_8896051.html",
        "img": {
            "0": "http://img1.rstcars.com/oldcars/audi/a6/big/8896051-1.jpg",
            "1": "http://img1.rstcars.com/oldcars/audi/a6/big/8896051-1.jpg"
        }
    },
    {
        "id": "_5wqi9x8fv",
        "number": 1,
        "title": "продам AUDI A4",
        "price": "244,000 грн",
        "year": "2005",
        "condition": "Хорошее",
        "engine": "2.0",
        "transmissionType": "Автомат",
        "location": "Одесса",
        "description": "Седан, Легковые, 4 дверей Пробег 258 тыс. км Двигатель 2 л. , Бензин Коробка передач Автомат Привод Передний Цвет Серебр",
        "mileage": " 258000 - пробег",
        "updateDate": "10.10.2018",
        "link": "http://rst.ua/oldcars/audi/a4/audi_a4_8485487.html",
        "img": {
            "0": "http://img.rstcars.com/oldcars/audi/a4/big/8485487-24.jpg",
            "1": "http://img.rstcars.com/oldcars/audi/a4/big/8485487-24.jpg"
        }
    },
    {
        "id": "_3cwiakprv",
        "number": 2,
        "title": "продам AUDI 100",
        "price": "101,000 грн",
        "year": "1991",
        "condition": "Хорошее",
        "engine": "2.3",
        "transmissionType": "Механика-5",
        "location": "Харьков",
        "description": "Продам авто Ауди 100 С4 в хорошем состоянии, все вопросы по телефону. торг",
        "mileage": " 317000 - пробег",
        "updateDate": "13.10.2018",
        "link": "http://rst.ua/oldcars/audi/100/audi_100_8202508.html",
        "img": {
            "0": "http://img.rstcars.com/oldcars/audi/100/big/8202508-7.jpg",
            "1": "http://img.rstcars.com/oldcars/audi/100/big/8202508-7.jpg"
        }
    },
    {
        "id": "_9x5e66ged",
        "number": 3,
        "title": "продам AUDI Q7",
        "price": "1,289,700 грн",
        "year": "2015",
        "condition": "Хорошее",
        "engine": "3.0",
        "transmissionType": "Автомат",
        "location": "Днепропетровск",
        "description": "Продам Audi Q7 (универсал В). Гаражное хранение, использовалось для домашних целей и поездок за рубеж. 1 владелец, авто ",
        "mileage": " 107000 - пробег",
        "updateDate": "09:39",
        "link": "http://rst.ua/oldcars/audi/q7/audi_q7_8630391.html",
        "img": {
            "0": "http://img1.rstcars.com/oldcars/audi/q7/big/8630391-1.jpg",
            "1": "http://img1.rstcars.com/oldcars/audi/q7/big/8630391-1.jpg"
        }
    },
    {
        "id": "_d6jjj85n7",
        "number": 4,
        "title": "продам AUDI Q7",
        "price": "448,600 грн",
        "year": "2007",
        "condition": "Хорошее",
        "engine": "4.2",
        "transmissionType": "Автомат",
        "location": "Луганск",
        "description": "Обмен с доплатой мне  не менее 5000у.е.Автомобиль в очень хорошем состоянии, новая резина, акб. Масло в акпп, двс, гидро",
        "mileage": " 154000 - пробег",
        "updateDate": "17:27",
        "link": "http://rst.ua/oldcars/audi/q7/audi_q7_8758250.html",
        "img": {
            "0": "http://img1.rstcars.com/oldcars/audi/q7/big/8758250-7.jpg",
            "1": "http://img1.rstcars.com/oldcars/audi/q7/big/8758250-7.jpg"
        }
    },
    {
        "id": "_xftf4hvxr",
        "number": 5,
        "title": "продам AUDI A6 premium ultra",
        "price": "558,000 грн",
        "year": "2012",
        "condition": "Хорошее",
        "engine": "2.0",
        "transmissionType": "Автомат",
        "location": "Киев",
        "description": "Продам автомобиль премиум сегмента в очень хорошем состоянии. Audi A6 . 2. 0turbo (211лс) . 2012г. в. (куплена в 2013). ",
        "mileage": " 137000 - пробег",
        "updateDate": "17:26",
        "link": "http://rst.ua/oldcars/audi/a6/audi_a6_8878389.html",
        "img": {
            "0": "http://img.rstcars.com/oldcars/audi/a6/big/8878389-1.jpg",
            "1": "http://img.rstcars.com/oldcars/audi/a6/big/8878389-1.jpg"
        }
    },
    {
        "id": "_cweavqrjy",
        "number": 6,
        "title": "продам AUDI A6",
        "price": "552,400 грн",
        "year": "2012",
        "condition": "Хорошее",
        "engine": "2.8",
        "transmissionType": "Автомат",
        "location": "Одесса",
        "description": "Официальная, куплена в Украине новой!!! Авто в отличном состояние, сервисное обслуживание, вложений не требует вообще!!!",
        "mileage": " 180000 - пробег",
        "updateDate": "16:35",
        "link": "http://rst.ua/oldcars/audi/a6/audi_a6_8889717.html",
        "img": {
            "0": "http://img.rstcars.com/oldcars/audi/a6/big/8889717-1.jpg",
            "1": "http://img.rstcars.com/oldcars/audi/a6/big/8889717-1.jpg"
        }
    },
    {
        "id": "_hg36p9wfd",
        "number": 7,
        "title": "продам AUDI A6",
        "price": "126,200 грн",
        "year": "1997",
        "condition": "Нормальное",
        "engine": "2.6",
        "transmissionType": "Автомат",
        "location": "Донецк",
        "description": "Все вопросы по тел больше интересен обмен",
        "mileage": " 390000 - пробег",
        "updateDate": "09:20",
        "link": "http://rst.ua/oldcars/audi/a6/audi_a6_8904946.html",
        "img": {
            "0": "http://img.rstcars.com/oldcars/audi/a6/big/8904946-1.jpg",
            "1": "http://img.rstcars.com/oldcars/audi/a6/big/8904946-1.jpg"
        }
    },
    {
        "id": "_8vc1swaf8",
        "number": 8,
        "title": "продам AUDI Q7",
        "price": "440,200 грн",
        "year": "2007",
        "condition": "Хорошее",
        "engine": "4.2",
        "transmissionType": "Автомат",
        "location": "Харьков",
        "description": "Я второй хозяин. Машина обслуживалась на Audi официал. Стоит газ Италия , стоит доп сигнализация(на фото видно) Машина и",
        "mileage": " 245000 - пробег",
        "updateDate": "18.10.2018",
        "link": "http://rst.ua/oldcars/audi/q7/audi_q7_8923062.html",
        "img": {
            "0": "http://img1.rstcars.com/oldcars/audi/q7/big/8923062-9.jpg",
            "1": "http://img1.rstcars.com/oldcars/audi/q7/big/8923062-9.jpg"
        }
    },
    {
        "id": "_88krx5leu",
        "number": 9,
        "title": "продам AUDI A6",
        "price": "448,600 грн",
        "year": "2006",
        "condition": "Хорошее",
        "engine": "2.0",
        "transmissionType": "Механика-6",
        "location": "Закарпатье",
        "description": "Бизнес-седан Audi A6 нового поколения слегка перешагнула за рамки бизнес-класса и вплотную приблизилась к флагмену A8. П",
        "mileage": " 230000 - пробег",
        "updateDate": "14:24",
        "link": "http://rst.ua/oldcars/audi/a6/audi_a6_8924780.html",
        "img": {
            "0": "http://img1.rstcars.com/oldcars/audi/a6/big/8924780-4.jpg",
            "1": "http://img1.rstcars.com/oldcars/audi/a6/big/8924780-4.jpg"
        }
    }
]